LICENSE
gitlab2nextclouddeck/GitlabAPI.py
gitlab2nextclouddeck/NextCloudDeckAPI.py
gitlab2nextclouddeck/__init__.py
gitlab2nextclouddeck/main.py
gitlab2nextclouddeck-0.1.11.dist-info/entry_points.txt
gitlab2nextclouddeck-0.1.11.dist-info/LICENSE
gitlab2nextclouddeck-0.1.11.dist-info/WHEEL
gitlab2nextclouddeck-0.1.11.dist-info/METADATA
gitlab2nextclouddeck-0.1.11.dist-info/RECORD
