Metadata-Version: 2.1
Name: gitlab2nextclouddeck
Version: 0.1.11
Summary: 
Home-page: https://yazcub.com
License: MIT
Keywords: gitlab,nextcloud,deck
Author: Ferit Cubukcuoglu
Author-email: info@yazcub.com
Requires-Python: >=3.8,<4.0
Classifier: License :: OSI Approved :: MIT License
Classifier: Programming Language :: Python :: 3
Classifier: Programming Language :: Python :: 3.8
Classifier: Programming Language :: Python :: 3.9
Requires-Dist: PyInquirer (>=1.0.3,<2.0.0)
Requires-Dist: progress (>=1.5,<2.0)
Requires-Dist: python-dotenv (>=0.17.1,<0.18.0)
Requires-Dist: python-gitlab (>=2.7.1,<3.0.0)
Requires-Dist: requests (>=2.25.1,<3.0.0)
Project-URL: Repository, https://github.com/yazcub
